Workbook
Name NativeTimeline_Order_Date: #N/A
Name NativeTimeline_Order_Date1: #N/A
Name Slicer_Brand: #N/A
Name Slicer_Category: #N/A
Name Slicer_Category1: #N/A
Name Slicer_Gender: #N/A
Name Slicer_Gender1: #N/A
Name Slicer_ORDER_MONTH: #N/A
Name Slicer_ORDER_MONTH1: #N/A
Name Slicer_Payment_Mode: #N/A
Name Slicer_Payment_Mode1: #N/A
Name Slicer_Region: #N/A
Name Slicer_Region1: #N/A

Sheet Raw Data
A1: Order ID | B1: ORDER MONTH | C1: Order Date | D1: Project Name | E1: Category | F1: Brand | G1: Region | H1: Channel | I1: Payment Mode | J1: Gender | K1: Units Sold | L1: Unit Price (₹) | M1: Total Revenue (₹) | N1: Discount (%) | O1: Discount Amount (₹) | P1: Net Revenue (₹) | Q1: Cost (₹) | R1: Gross Profit (₹) | S1: Returns | T1: Return Amount (₹) | U1: Customer Rating
A2: ORD00126 | B2: =TEXT(C2,"MMMM") -> January | C2: 44927 | D2: AJIO Back to Campus | E2: Sports | F2: Zara | G2: South | H2: Mobile Web | I2: COD | J2: Male | K2: 11 | L2: 3440 | M2: 37840 | N2: 50 | O2: 18920 | P2: 18920 | Q2: 13124 | R2: 5796 | S2: 0 | T2: 0 | U2: 4.9
A3: ORD00272 | B3: =TEXT(C3,"MMMM") -> January | C3: 44928 | D3: AJIO Summer Splash | E3: Beauty | F3: Nike | G3: East | H3: Mobile Web | I3: Wallet | J3: Female | K3: 4 | L3: 755 | M3: 3020 | N3: 15 | O3: 453 | P3: 2567 | Q3: 1265 | R3: 1302 | S3: 1 | T3: 642 | U3: 4.9
A4: ORD00367 | B4: =TEXT(C4,"MMMM") -> January | C4: 44932 | D4: AJIO Sports Carnival | E4: Footwear | F4: HERE&NOW | G4: East | H4: App | I4: Credit Card | J4: Unisex | K4: 9 | L4: 2723 | M4: 24507 | N4: 15 | O4: 3676 | P4: 20831 | Q4: 12578 | R4: 8253 | S4: 2 | T4: 4629 | U4: 2.6
A5: ORD00236 | B5: =TEXT(C5,"MMMM") -> January | C5: 44934 | D5: AJIO Fashion Fiesta | E5: Accessories | F5: H&M | G5: North | H5: App | I5: COD | J5: Unisex | K5: 5 | L5: 3253 | M5: 16265 | N5: 50 | O5: 8132 | P5: 8133 | Q5: 5220 | R5: 2913 | S5: 1 | T5: 1626 | U5: 4.3
A6: ORD00399 | B6: =TEXT(C6,"MMMM") -> January | C6: 44934 | D6: AJIO Fashion Fiesta | E6: Footwear | F6: Levis | G6: Central | H6: App | I6: COD | J6: Male | K6: 1 | L6: 4853 | M6: 4853 | N6: 40 | O6: 1941 | P6: 2912 | Q6: 1812 | R6: 1100 | S6: 0 | T6: 0 | U6: 3.4
A7: ORD00482 | B7: =TEXT(C7,"MMMM") -> January | C7: 44934 | D7: AJIO Sports Carnival | E7: Home & Living | F7: Nike | G7: Central | H7: App | I7: Wallet | J7: Unisex | K7: 3 | L7: 3397 | M7: 10191 | N7: 25 | O7: 2548 | P7: 7643 | Q7: 4983 | R7: 2660 | S7: 1 | T7: 2548 | U7: 4.5
A8: ORD00413 | B8: =TEXT(C8,"MMMM") -> January | C8: 44935 | D8: AJIO Back to Campus | E8: Sports | F8: Adidas | G8: East | H8: App | I8: UPI | J8: Male | K8: 4 | L8: 4321 | M8: 17284 | N8: 0 | O8: 0 | P8: 17284 | Q8: 11112 | R8: 6172 | S8: 1 | T8: 4321 | U8: 4.8
A9: ORD00107 | B9: =TEXT(C9,"MMMM") -> January | C9: 44937 | D9: AJIO New Year Blowout | E9: Accessories | F9: Adidas | G9: Central | H9: Website | I9: UPI | J9: Male | K9: 7 | L9: 4268 | M9: 29876 | N9: 15 | O9: 4481 | P9: 25395 | Q9: 14194 | R9: 11201 | S9: 1 | T9: 3628 | U9: 3.8
A10: ORD00082 | B10: =TEXT(C10,"MMMM") -> January | C10: 44938 | D10: AJIO End of Season | E10: Kids | F10: Van Heusen | G10: East | H10: App | I10: Wallet | J10: Unisex | K10: 13 | L10: 3799 | M10: 49387 | N10: 0 | O10: 0 | P10: 49387 | Q10: 33467 | R10: 15920 | S10: 3 | T10: 11397 | U10: 4.6
A11: ORD00172 | B11: =TEXT(C11,"MMMM") -> January | C11: 44938 | D11: AJIO Fashion Fiesta | E11: Beauty | F11: Levis | G11: North | H11: Mobile Web | I11: Debit Card | J11: Unisex | K11: 2 | L11: 512 | M11: 1024 | N11: 25 | O11: 256 | P11: 768 | Q11: 480 | R11: 288 | S11: 0 | T11: 0 | U11: 4.8
A12: ORD00211 | B12: =TEXT(C12,"MMMM") -> January | C12: 44938 | D12: AJIO Sports Carnival | E12: Kids | F12: Zara | G12: North | H12: Mobile Web | I12: Debit Card | J12: Unisex | K12: 4 | L12: 2724 | M12: 10896 | N12: 50 | O12: 5448 | P12: 5448 | Q12: 2670 | R12: 2778 | S12: 1 | T12: 1362 | U12: 4.9
A13: ORD00386 | B13: =TEXT(C13,"MMMM") -> January | C13: 44938 | D13: AJIO Big Bold Sale | E13: Footwear | F13: H&M | G13: East | H13: Mobile Web | I13: Credit Card | J13: Male | K13: 3 | L13: 2165 | M13: 6495 | N13: 5 | O13: 325 | P13: 6170 | Q13: 2875 | R13: 3295 | S13: 1 | T13: 2057 | U13: 3.9
... A501: ORD00440 | B501: =TEXT(C501,"MMMM") -> December | C501: 45291 | D501: AJIO Summer Splash | E501: Footwear | F501: Roadster | G501: North | H501: Website | I501: UPI | J501: Unisex | K501: 11 | L501: 4563 | M501: 50193 | N501: 10 | O501: 5019 | P501: 45174 | Q501: 28441 | R501: 16733 | S501: 0 | T501: 0 | U501: 2.7

Sheet KPI Dashboard
A1: 🛍 AJIO SALES KPI DASHBOARD
A3: Full Year Performance Summary | 500 Orders | FY Analytics
A5: KEY PERFORMANCE INDICATORS
A6: ₹ TOTAL REVENUE | D6: ₹ NET REVENUE | G6: ₹ GROSS PROFIT | J6: # TOTAL ORDERS | M6: 📦 UNITS SOLD | P6: 🔄 TOTAL RETURNS | S6: ⭐ AVG RATING
A7: =SUM('Raw Data'!M:M) -> 10641857 | D7: =SUM('Raw Data'!P:P) -> 8454342 | G7: =SUM('Raw Data'!R:R) -> 3599485 | J7: =COUNTA('Raw Data'!A:A)-1 -> 500 | M7: =SUM('Raw Data'!K:K) -> 3897 | P7: =SUM('Raw Data'!S:S) -> 472 | S7: =AVERAGE('Raw Data'!U:U) -> 3.7242
A9: PROFIT MARGIN % | D9: AVG ORDER VALUE (₹) | G9: RETURN RATE % | J9: DISCOUNT IMPACT (₹) | M9: AVG UNITS/ORDER | P9: COST RATIO % | S9: NET MARGIN %
A10: =SUM('Raw Data'!R:R)/SUM('Raw Data'!M:M) -> 0.33823843 | D10: =SUM('Raw Data'!P:P)/(COUNTA('Raw Data'!A:A)-1) -> 16908.684 | G10: =SUM('Raw Data'!S:S)/(COUNTA('Raw Data'!A:A)-1) -> 0.944 | J10: =SUM('Raw Data'!O:O) -> 2187515 | M10: =SUM('Raw Data'!K:K)/(COUNTA('Raw Data'!A:A)-1) -> 7.794 | P10: =SUM('Raw Data'!Q:Q)/SUM('Raw Data'!M:M) -> 0.45620393 | S10: =SUM('Raw Data'!P:P)/SUM('Raw Data'!M:M) -> 0.79444236
A13: MONTHLY PERFORMANCE BREAKDOWN | V13: COUNTIF('Raw Data'!B:B,"January"
A14: MONTH | C14: ORDERS | E14: UNITS SOLD | G14: REVENUE (₹) | I14: NET REVENUE (₹) | K14: GROSS PROFIT (₹) | M14: PROFIT MARGIN | O14: RETURNS | Q14: RETURN RATE | S14: AVG RATING
A15: January | C15: =COUNTIF('Raw Data'!B:B,"JANUARY") -> 31 | E15: =SUMIF('Raw Data'!B:B,"JANUARY",'Raw Data'!K:K) -> 227 | G15: =SUMIF('Raw Data'!B:B,"January",'Raw Data'!M:M) -> 558337 | I15: =SUMIF('Raw Data'!B:B,"January",'Raw Data'!P:P) -> 414702 | K15: =SUMIF('Raw Data'!B:B,"January",'Raw Data'!R:R) -> 179440 | M15: =IFERROR(SUMIF('Raw Data'!B:B,"JANUARY",'Raw Data'!R:R)/SUMIF('Raw Data'!B:B,"JANUARY",'Raw Data'!M:M),0) -> 0.32138296 | O15: =SUMIF('Raw Data'!B:B,"January",'Raw Data'!S:S) -> 33 | Q15: V | S15: =IFERROR(AVERAGEIF('Raw Data'!B:B,"January",'Raw Data'!U:U),0) -> 3.9548387
A16: February | C16: =COUNTIF('Raw Data'!B:B,"February") -> 45 | E16: =SUMIF('Raw Data'!B:B,"February",'Raw Data'!K:K) -> 348 | G16: =SUMIF('Raw Data'!B:B,"February",'Raw Data'!M:M) -> 920237 | I16: =SUMIF('Raw Data'!B:B,"February",'Raw Data'!P:P) -> 758573 | K16: =SUMIF('Raw Data'!B:B,"February",'Raw Data'!R:R) -> 326369 | M16: =IFERROR(SUMIF('Raw Data'!B:B,"February",'Raw Data'!R:R)/SUMIF('Raw Data'!B:B,"February",'Raw Data'!M:M),0) -> 0.35465755 | O16: =SUMIF('Raw Data'!B:B,"February",'Raw Data'!S:S) -> 36 | Q16: =IFERROR(SUMIF('Raw Data'!B:B,"February",'Raw Data'!S:S)/COUNTIF('Raw Data'!B:B,"February"),0) -> 0.8 | S16: =IFERROR(AVERAGEIF('Raw Data'!B:B,"February",'Raw Data'!U:U),0) -> 3.7511111
A17: March | C17: =COUNTIF('Raw Data'!B:B,"March") -> 32 | E17: =SUMIF('Raw Data'!B:B,"March",'Raw Data'!K:K) -> 261 | G17: =SUMIF('Raw Data'!B:B,"March",'Raw Data'!M:M) -> 590233 | I17: =SUMIF('Raw Data'!B:B,"March",'Raw Data'!P:P) -> 490455 | K17: =SUMIF('Raw Data'!B:B,"March",'Raw Data'!R:R) -> 210937 | M17: =IFERROR(SUMIF('Raw Data'!B:B,"March",'Raw Data'!R:R)/SUMIF('Raw Data'!B:B,"March",'Raw Data'!M:M),0) -> 0.3573792 | O17: =SUMIF('Raw Data'!B:B,"March",'Raw Data'!S:S) -> 25 | Q17: =IFERROR(SUMIF('Raw Data'!B:B,"March",'Raw Data'!S:S)/COUNTIF('Raw Data'!B:B,"March"),0) -> 0.78125 | S17: =IFERROR(AVERAGEIF('Raw Data'!B:B,"March",'Raw Data'!U:U),0) -> 3.884375
A18: April | C18: =COUNTIF('Raw Data'!B:B,"April") -> 41 | E18: =SUMIF('Raw Data'!B:B,"April",'Raw Data'!K:K) -> 324 | G18: =SUMIF('Raw Data'!B:B,"April",'Raw Data'!M:M) -> 828538 | I18: =SUMIF('Raw Data'!B:B,"April",'Raw Data'!P:P) -> 648341 | K18: =SUMIF('Raw Data'!B:B,"April",'Raw Data'!R:R) -> 260451 | M18: =IFERROR(SUMIF('Raw Data'!B:B,"April",'Raw Data'!R:R)/SUMIF('Raw Data'!B:B,"April",'Raw Data'!M:M),0) -> 0.3143501 | O18: =SUMIF('Raw Data'!B:B,"April",'Raw Data'!S:S) -> 39 | Q18: =IFERROR(SUMIF('Raw Data'!B:B,"April",'Raw Data'!S:S)/COUNTIF('Raw Data'!B:B,"April"),0) -> 0.95121951 | S18: =IFERROR(AVERAGEIF('Raw Data'!B:B,"April",'Raw Data'!U:U),0) -> 3.7853659
A19: May | C19: =COUNTIF('Raw Data'!B:B,"May") -> 52 | E19: =SUMIF('Raw Data'!B:B,"May",'Raw Data'!K:K) -> 377 | G19: =SUMIF('Raw Data'!B:B,"May",'Raw Data'!M:M) -> 1122674 | I19: =SUMIF('Raw Data'!B:B,"May",'Raw Data'!P:P) -> 893286 | K19: =SUMIF('Raw Data'!B:B,"May",'Raw Data'!R:R) -> 377564 | M19: =IFERROR(SUMIF('Raw Data'!B:B,"May",'Raw Data'!R:R)/SUMIF('Raw Data'!B:B,"May",'Raw Data'!M:M),0) -> 0.33630778 | O19: =SUMIF('Raw Data'!B:B,"May",'Raw Data'!S:S) -> 50 | Q19: =IFERROR(SUMIF('Raw Data'!B:B,"May",'Raw Data'!S:S)/COUNTIF('Raw Data'!B:B,"May"),0) -> 0.96153846 | S19: =IFERROR(AVERAGEIF('Raw Data'!B:B,"May",'Raw Data'!U:U),0) -> 3.6288462
A20: June | C20: =COUNTIF('Raw Data'!B:B,"June") -> 29 | E20: =SUMIF('Raw Data'!B:B,"June",'Raw Data'!K:K) -> 181 | G20: =SUMIF('Raw Data'!B:B,"June",'Raw Data'!M:M) -> 520572 | I20: =SUMIF('Raw Data'!B:B,"June",'Raw Data'!P:P) -> 418150 | K20: =SUMIF('Raw Data'!B:B,"June",'Raw Data'!R:R) -> 179575 | M20: =IFERROR(SUMIF('Raw Data'!B:B,"June",'Raw Data'!R:R)/SUMIF('Raw Data'!B:B,"June",'Raw Data'!M:M),0) -> 0.34495709 | O20: =SUMIF('Raw Data'!B:B,"June",'Raw Data'!S:S) -> 26 | Q20: =IFERROR(SUMIF('Raw Data'!B:B,"June",'Raw Data'!S:S)/COUNTIF('Raw Data'!B:B,"June"),0) -> 0.89655172 | S20: =IFERROR(AVERAGEIF('Raw Data'!B:B,"June",'Raw Data'!U:U),0) -> 3.4586207
A21: July | C21: =COUNTIF('Raw Data'!B:B,"July") -> 46 | E21: =SUMIF('Raw Data'!B:B,"July",'Raw Data'!K:K) -> 393 | G21: =SUMIF('Raw Data'!B:B,"July",'Raw Data'!M:M) -> 1120123 | I21: =SUMIF('Raw Data'!B:B,"July",'Raw Data'!P:P) -> 919842 | K21: =SUMIF('Raw Data'!B:B,"July",'Raw Data'!R:R) -> 386509 | M21: =IFERROR(SUMIF('Raw Data'!B:B,"July",'Raw Data'!R:R)/SUMIF('Raw Data'!B:B,"July",'Raw Data'!M:M),0) -> 0.34505943 | O21: =SUMIF('Raw Data'!B:B,"July",'Raw Data'!S:S) -> 48 | Q21: =IFERROR(SUMIF('Raw Data'!B:B,"July",'Raw Data'!S:S)/COUNTIF('Raw Data'!B:B,"July"),0) -> 1.0434783 | S21: =IFERROR(AVERAGEIF('Raw Data'!B:B,"July",'Raw Data'!U:U),0) -> 3.6956522
A22: August | C22: =COUNTIF('Raw Data'!B:B,"August") -> 42 | E22: =SUMIF('Raw Data'!B:B,"August",'Raw Data'!K:K) -> 330 | G22: =SUMIF('Raw Data'!B:B,"August",'Raw Data'!M:M) -> 888761 | I22: =SUMIF('Raw Data'!B:B,"August",'Raw Data'!P:P) -> 704148 | K22: =SUMIF('Raw Data'!B:B,"August",'Raw Data'!R:R) -> 296397 | M22: =IFERROR(SUMIF('Raw Data'!B:B,"August",'Raw Data'!R:R)/SUMIF('Raw Data'!B:B,"August",'Raw Data'!M:M),0) -> 0.33349461 | O22: =SUMIF('Raw Data'!B:B,"August",'Raw Data'!S:S) -> 43 | Q22: =IFERROR(SUMIF('Raw Data'!B:B,"August",'Raw Data'!S:S)/COUNTIF('Raw Data'!B:B,"August"),0) -> 1.0238095 | S22: =IFERROR(AVERAGEIF('Raw Data'!B:B,"August",'Raw Data'!U:U),0) -> 3.6857143
A23: September | C23: =COUNTIF('Raw Data'!B:B,"September") -> 47 | E23: =SUMIF('Raw Data'!B:B,"September",'Raw Data'!K:K) -> 341 | G23: =SUMIF('Raw Data'!B:B,"September",'Raw Data'!M:M) -> 964038 | I23: =SUMIF('Raw Data'!B:B,"September",'Raw Data'!P:P) -> 780859 | K23: =SUMIF('Raw Data'!B:B,"September",'Raw Data'!R:R) -> 339145 | M23: =IFERROR(SUMIF('Raw Data'!B:B,"September",'Raw Data'!R:R)/SUMIF('Raw Data'!B:B,"September",'Raw Data'!M:M),0) -> 0.3517963 | O23: =SUMIF('Raw Data'!B:B,"September",'Raw Data'!S:S) -> 43 | Q23: =IFERROR(SUMIF('Raw Data'!B:B,"September",'Raw Data'!S:S)/COUNTIF('Raw Data'!B:B,"September"),0) -> 0.91489362 | S23: =IFERROR(AVERAGEIF('Raw Data'!B:B,"September",'Raw Data'!U:U),0) -> 3.6191489
A24: October | C24: =COUNTIF('Raw Data'!B:B,"October") -> 50 | E24: =SUMIF('Raw Data'!B:B,"October",'Raw Data'!K:K) -> 383 | G24: =SUMIF('Raw Data'!B:B,"October",'Raw Data'!M:M) -> 977579 | I24: =SUMIF('Raw Data'!B:B,"October",'Raw Data'!P:P) -> 746692 | K24: =SUMIF('Raw Data'!B:B,"October",'Raw Data'!R:R) -> 325402 | M24: =IFERROR(SUMIF('Raw Data'!B:B,"October",'Raw Data'!R:R)/SUMIF('Raw Data'!B:B,"October",'Raw Data'!M:M),0) -> 0.33286517 | O24: =SUMIF('Raw Data'!B:B,"October",'Raw Data'!S:S) -> 39 | Q24: =IFERROR(SUMIF('Raw Data'!B:B,"October",'Raw Data'!S:S)/COUNTIF('Raw Data'!B:B,"October"),0) -> 0.78 | S24: =IFERROR(AVERAGEIF('Raw Data'!B:B,"October",'Raw Data'!U:U),0) -> 3.58
A25: November | C25: =COUNTIF('Raw Data'!B:B,"November") -> 37 | E25: =SUMIF('Raw Data'!B:B,"November",'Raw Data'!K:K) -> 309 | G25: =SUMIF('Raw Data'!B:B,"November",'Raw Data'!M:M) -> 925078 | I25: =SUMIF('Raw Data'!B:B,"November",'Raw Data'!P:P) -> 708636 | K25: =SUMIF('Raw Data'!B:B,"November",'Raw Data'!R:R) -> 303300 | M25: =IFERROR(SUMIF('Raw Data'!B:B,"November",'Raw Data'!R:R)/SUMIF('Raw Data'!B:B,"November",'Raw Data'!M:M),0) -> 0.32786424 | O25: =SUMIF('Raw Data'!B:B,"November",'Raw Data'!S:S) -> 40 | Q25: =IFERROR(SUMIF('Raw Data'!B:B,"November",'Raw Data'!S:S)/COUNTIF('Raw Data'!B:B,"November"),0) -> 1.0810811 | S25: =IFERROR(AVERAGEIF('Raw Data'!B:B,"November",'Raw Data'!U:U),0) -> 3.8648649
A26: December | C26: =COUNTIF('Raw Data'!B:B,"December") -> 48 | E26: =SUMIF('Raw Data'!B:B,"December",'Raw Data'!K:K) -> 423 | G26: =SUMIF('Raw Data'!B:B,"December",'Raw Data'!M:M) -> 1225687 | I26: =SUMIF('Raw Data'!B:B,"December",'Raw Data'!P:P) -> 970658 | K26: =SUMIF('Raw Data'!B:B,"December",'Raw Data'!R:R) -> 414396 | M26: =IFERROR(SUMIF('Raw Data'!B:B,"December",'Raw Data'!R:R)/SUMIF('Raw Data'!B:B,"December",'Raw Data'!M:M),0) -> 0.33809284 | O26: =SUMIF('Raw Data'!B:B,"December",'Raw Data'!S:S) -> 50 | Q26: =IFERROR(SUMIF('Raw Data'!B:B,"December",'Raw Data'!S:S)/COUNTIF('Raw Data'!B:B,"December"),0) -> 1.0416667 | S26: =IFERROR(AVERAGEIF('Raw Data'!B:B,"December",'Raw Data'!U:U),0) -> 3.8604167
A27: TOTAL / AVG | C27: =SUM(C15:C26) -> 500 | E27: =SUM(E15:E26) -> 3897 | G27: =SUM(G15:G26) -> 10641857 | I27: =SUM(I15:I26) -> 8454342 | K27: =SUM(K15:K26) -> 3599485 | M27: =AVERAGE(M15:M26) -> 0.33818394 | O27: =SUM(O15:O26) -> 472 | Q27: =AVERAGE(Q15:Q26) -> 0.93413535 | S27: =AVERAGE(S15:S26) -> 3.7307462
A29: REVENUE BY CATEGORY | L29: REVENUE BY REGION
A30: CATEGORY | B30: ORDERS | D30: REVENUE (₹) | F30: NET REVENUE | H30: PROFIT | J30: MARGIN % | L30: REGION | N30: ORDERS | P30: REVENUE (₹) | R30: NET REVENUE | T30: AVG RATING
A31: Sports | B31: =COUNTIF('Raw Data'!E:E,"Sports") -> 72 | D31: =SUMIF('Raw Data'!E:E,"Sports",'Raw Data'!M:M) -> 1368287 | F31: =SUMIF('Raw Data'!E:E,"Sports",'Raw Data'!P:P) -> 1085922 | H31: =SUMIF('Raw Data'!E:E,"Sports",'Raw Data'!R:R) -> 449312 | J31: =IFERROR(SUMIF('Raw Data'!E:E,"Sports",'Raw Data'!R:R)/SUMIF('Raw Data'!E:E,"Sports",'Raw Data'!M:M),0) -> 0.32837555 | L31: North | N31: =COUNTIF('Raw Data'!G:G,"North") -> 98 | P31: =SUMIF('Raw Data'!G:G,"North",'Raw Data'!M:M) -> 2197953 | R31: =SUMIF('Raw Data'!G:G,"North",'Raw Data'!P:P) -> 1769552 | T31: =IFERROR(AVERAGEIF('Raw Data'!G:G,"North",'Raw Data'!U:U),0) -> 3.6265306
A32: Beauty | B32: =COUNTIF('Raw Data'!E:E,"Beauty") -> 79 | D32: =SUMIF('Raw Data'!E:E,"Beauty",'Raw Data'!M:M) -> 1562443 | F32: =SUMIF('Raw Data'!E:E,"Beauty",'Raw Data'!P:P) -> 1287318 | H32: =SUMIF('Raw Data'!E:E,"Beauty",'Raw Data'!R:R) -> 542159 | J32: =IFERROR(SUMIF('Raw Data'!E:E,"Beauty",'Raw Data'!R:R)/SUMIF('Raw Data'!E:E,"Beauty",'Raw Data'!M:M),0) -> 0.34699442 | L32: South | N32: =COUNTIF('Raw Data'!G:G,"South") -> 102 | P32: =SUMIF('Raw Data'!G:G,"South",'Raw Data'!M:M) -> 2245588 | R32: =SUMIF('Raw Data'!G:G,"South",'Raw Data'!P:P) -> 1727059 | T32: =IFERROR(AVERAGEIF('Raw Data'!G:G,"South",'Raw Data'!U:U),0) -> 3.7941176
A33: Footwear | B33: =COUNTIF('Raw Data'!E:E,"Footwear") -> 64 | D33: =SUMIF('Raw Data'!E:E,"Footwear",'Raw Data'!M:M) -> 1685692 | F33: =SUMIF('Raw Data'!E:E,"Footwear",'Raw Data'!P:P) -> 1306363 | H33: =SUMIF('Raw Data'!E:E,"Footwear",'Raw Data'!R:R) -> 579584 | J33: =IFERROR(SUMIF('Raw Data'!E:E,"Footwear",'Raw Data'!R:R)/SUMIF('Raw Data'!E:E,"Footwear",'Raw Data'!M:M),0) -> 0.34382556 | L33: East | N33: =COUNTIF('Raw Data'!G:G,"East") -> 85 | P33: =SUMIF('Raw Data'!G:G,"East",'Raw Data'!M:M) -> 1833265 | R33: =SUMIF('Raw Data'!G:G,"East",'Raw Data'!P:P) -> 1483592 | T33: =IFERROR(AVERAGEIF('Raw Data'!G:G,"East",'Raw Data'!U:U),0) -> 3.7164706
A34: Accessories | B34: =COUNTIF('Raw Data'!E:E,"Accessories") -> 68 | D34: =SUMIF('Raw Data'!E:E,"Accessories",'Raw Data'!M:M) -> 1465218 | F34: =SUMIF('Raw Data'!E:E,"Accessories",'Raw Data'!P:P) -> 1157667 | H34: =SUMIF('Raw Data'!E:E,"Accessories",'Raw Data'!R:R) -> 480942 | J34: =IFERROR(SUMIF('Raw Data'!E:E,"Accessories",'Raw Data'!R:R)/SUMIF('Raw Data'!E:E,"Accessories",'Raw Data'!M:M),0) -> 0.32823921 | L34: West | N34: =COUNTIF('Raw Data'!G:G,"West") -> 110 | P34: =SUMIF('Raw Data'!G:G,"West",'Raw Data'!M:M) -> 2165577 | R34: =SUMIF('Raw Data'!G:G,"West",'Raw Data'!P:P) -> 1762720 | T34: =IFERROR(AVERAGEIF('Raw Data'!G:G,"West",'Raw Data'!U:U),0) -> 3.7327273
A35: Home & Living | B35: =COUNTIF('Raw Data'!E:E,"Home & Living") -> 74 | D35: =SUMIF('Raw Data'!E:E,"Home & Living",'Raw Data'!M:M) -> 1701828 | F35: =SUMIF('Raw Data'!E:E,"Home & Living",'Raw Data'!P:P) -> 1359315 | H35: =SUMIF('Raw Data'!E:E,"Home & Living",'Raw Data'!R:R) -> 582199 | J35: =IFERROR(SUMIF('Raw Data'!E:E,"Home & Living",'Raw Data'!R:R)/SUMIF('Raw Data'!E:E,"Home & Living",'Raw Data'!M:M),0) -> 0.34210214 | L35: Central | N35: =COUNTIF('Raw Data'!G:G,"Central") -> 105 | P35: =SUMIF('Raw Data'!G:G,"Central",'Raw Data'!M:M) -> 2199474 | R35: =SUMIF('Raw Data'!G:G,"Central",'Raw Data'!P:P) -> 1711419 | T35: =IFERROR(AVERAGEIF('Raw Data'!G:G,"Central",'Raw Data'!U:U),0) -> 3.7447619
A36: Kids | B36: =COUNTIF('Raw Data'!E:E,"Kids") -> 83 | D36: =SUMIF('Raw Data'!E:E,"Kids",'Raw Data'!M:M) -> 1709049 | F36: =SUMIF('Raw Data'!E:E,"Kids",'Raw Data'!P:P) -> 1314578 | H36: =SUMIF('Raw Data'!E:E,"Kids",'Raw Data'!R:R) -> 563151 | J36: =IFERROR(SUMIF('Raw Data'!E:E,"Kids",'Raw Data'!R:R)/SUMIF('Raw Data'!E:E,"Kids",'Raw Data'!M:M),0) -> 0.32951132
A37: Clothing | B37: =COUNTIF('Raw Data'!E:E,"Clothing") -> 60 | D37: =SUMIF('Raw Data'!E:E,"Clothing",'Raw Data'!M:M) -> 1149340 | F37: =SUMIF('Raw Data'!E:E,"Clothing",'Raw Data'!P:P) -> 943179 | H37: =SUMIF('Raw Data'!E:E,"Clothing",'Raw Data'!R:R) -> 402138 | J37: =IFERROR(SUMIF('Raw Data'!E:E,"Clothing",'Raw Data'!R:R)/SUMIF('Raw Data'!E:E,"Clothing",'Raw Data'!M:M),0) -> 0.34988602
A39: ORDERS BY CHANNEL | L39: ORDERS BY PAYMENT MODE
A40: CHANNEL | C40: ORDERS | E40: REVENUE (₹) | G40: NET REVENUE | I40: MARGIN % | L40: PAYMENT MODE | N40: ORDERS | P40: REVENUE (₹) | R40: NET REVENUE
A41: App | C41: =COUNTIF('Raw Data'!H:H,"App") -> 162 | E41: =SUMIF('Raw Data'!H:H,"App",'Raw Data'!M:M) -> 3276893 | G41: =SUMIF('Raw Data'!H:H,"App",'Raw Data'!P:P) -> 2502400 | I41: =IFERROR(SUMIF('Raw Data'!H:H,"App",'Raw Data'!R:R)/SUMIF('Raw Data'!H:H,"App",'Raw Data'!M:M),0) -> 0.32523033 | L41: COD | N41: =COUNTIF('Raw Data'!I:I,"COD") -> 104 | P41: =SUMIF('Raw Data'!I:I,"COD",'Raw Data'!M:M) -> 1954692 | R41: =SUMIF('Raw Data'!I:I,"COD",'Raw Data'!P:P) -> 1522207
A42: Mobile Web | C42: =COUNTIF('Raw Data'!H:H,"Mobile Web") -> 188 | E42: =SUMIF('Raw Data'!H:H,"Mobile Web",'Raw Data'!M:M) -> 4423552 | G42: =SUMIF('Raw Data'!H:H,"Mobile Web",'Raw Data'!P:P) -> 3551487 | I42: =IFERROR(SUMIF('Raw Data'!H:H,"Mobile Web",'Raw Data'!R:R)/SUMIF('Raw Data'!H:H,"Mobile Web",'Raw Data'!M:M),0) -> 0.34357367 | L42: UPI | N42: =COUNTIF('Raw Data'!I:I,"UPI") -> 122 | P42: =SUMIF('Raw Data'!I:I,"UPI",'Raw Data'!M:M) -> 2561013 | R42: =SUMIF('Raw Data'!I:I,"UPI",'Raw Data'!P:P) -> 2067350
A43: Website | C43: =COUNTIF('Raw Data'!H:H,"Website") -> 150 | E43: =SUMIF('Raw Data'!H:H,"Website",'Raw Data'!M:M) -> 2941412 | G43: =SUMIF('Raw Data'!H:H,"Website",'Raw Data'!P:P) -> 2400455 | I43: =IFERROR(SUMIF('Raw Data'!H:H,"Website",'Raw Data'!R:R)/SUMIF('Raw Data'!H:H,"Website",'Raw Data'!M:M),0) -> 0.34470656 | L43: Credit Card | N43: =COUNTIF('Raw Data'!I:I,"Credit Card") -> 82 | P43: =SUMIF('Raw Data'!I:I,"Credit Card",'Raw Data'!M:M) -> 1563147 | R43: =SUMIF('Raw Data'!I:I,"Credit Card",'Raw Data'!P:P) -> 1222019
L44: Debit Card | N44: =COUNTIF('Raw Data'!I:I,"Debit Card") -> 84 | P44: =SUMIF('Raw Data'!I:I,"Debit Card",'Raw Data'!M:M) -> 1913627 | R44: =SUMIF('Raw Data'!I:I,"Debit Card",'Raw Data'!P:P) -> 1531556
L45: Wallet | N45: =COUNTIF('Raw Data'!I:I,"Wallet") -> 108 | P45: =SUMIF('Raw Data'!I:I,"Wallet",'Raw Data'!M:M) -> 2649378 | R45: =SUMIF('Raw Data'!I:I,"Wallet",'Raw Data'!P:P) -> 2111210

Sheet Sheet1
A1: Order ID | B1: ORDER MONTH | C1: Order Date | D1: Project Name | E1: Category | F1: Brand | G1: Region | H1: Channel | I1: Payment Mode | J1: Gender | K1: Units Sold | L1: Unit Price (₹) | M1: Revenue (₹) | N1: Discount (%) | O1: Discount Amount (₹) | P1: Net Revenue (₹) | Q1: Cost (₹) | R1: Gross Profit (₹) | S1: Returns | T1: Return Amount (₹) | U1: Customer Rating
A2: ORD00126 | B2: January | C2: 44927 | D2: AJIO Back to Campus | E2: Sports | F2: Zara | G2: South | H2: Mobile Web | I2: COD | J2: Male | K2: 11 | L2: 3440 | M2: 37840 | N2: 50 | O2: 18920 | P2: 18920 | Q2: 13124 | R2: 5796 | S2: 0 | T2: 0 | U2: 4.9
A3: ORD00236 | B3: January | C3: 44934 | D3: AJIO Fashion Fiesta | E3: Accessories | F3: H&M | G3: North | H3: App | I3: COD | J3: Unisex | K3: 5 | L3: 3253 | M3: 16265 | N3: 50 | O3: 8132 | P3: 8133 | Q3: 5220 | R3: 2913 | S3: 1 | T3: 1626 | U3: 4.3
A4: ORD00399 | B4: January | C4: 44934 | D4: AJIO Fashion Fiesta | E4: Footwear | F4: Levis | G4: Central | H4: App | I4: COD | J4: Male | K4: 1 | L4: 4853 | M4: 4853 | N4: 40 | O4: 1941 | P4: 2912 | Q4: 1812 | R4: 1100 | S4: 0 | T4: 0 | U4: 3.4
A5: ORD00281 | B5: January | C5: 44946 | D5: AJIO Summer Splash | E5: Beauty | F5: Zara | G5: South | H5: App | I5: COD | J5: Female | K5: 15 | L5: 2049 | M5: 30735 | N5: 25 | O5: 7684 | P5: 23051 | Q5: 15083 | R5: 7968 | S5: 2 | T5: 3074 | U5: 3.3
A6: ORD00103 | B6: January | C6: 44952 | D6: AJIO New Year Blowout | E6: Home & Living | F6: Nike | G6: East | H6: Website | I6: COD | J6: Female | K6: 10 | L6: 2377 | M6: 23770 | N6: 20 | O6: 4754 | P6: 19016 | Q6: 9582 | R6: 9434 | S6: 2 | T6: 3803 | U6: 2.8
A7: ORD00255 | B7: January | C7: 44952 | D7: AJIO End of Season | E7: Footwear | F7: Tokyo Talkies | G7: West | H7: Mobile Web | I7: COD | J7: Female | K7: 1 | L7: 2098 | M7: 2098 | N7: 30 | O7: 629 | P7: 1469 | Q7: 725 | R7: 744 | S7: 0 | T7: 0 | U7: 4.8
A8: ORD00372 | B8: February | C8: 44961 | D8: AJIO Festive Rush | E8: Beauty | F8: H&M | G8: South | H8: Website | I8: COD | J8: Female | K8: 9 | L8: 2817 | M8: 25353 | N8: 20 | O8: 5071 | P8: 20282 | Q8: 10386 | R8: 9896 | S8: 0 | T8: 0 | U8: 3.5
A9: ORD00106 | B9: February | C9: 44963 | D9: AJIO New Year Blowout | E9: Beauty | F9: Puma | G9: West | H9: App | I9: COD | J9: Male | K9: 14 | L9: 1770 | M9: 24780 | N9: 30 | O9: 7434 | P9: 17346 | Q9: 10292 | R9: 7054 | S9: 3 | T9: 3717 | U9: 3.2
A10: ORD00462 | B10: February | C10: 44963 | D10: AJIO New Year Blowout | E10: Accessories | F10: Tokyo Talkies | G10: East | H10: Mobile Web | I10: COD | J10: Male | K10: 3 | L10: 435 | M10: 1305 | N10: 0 | O10: 0 | P10: 1305 | Q10: 622 | R10: 683 | S10: 0 | T10: 0 | U10: 2.7
A11: ORD00191 | B11: February | C11: 44974 | D11: AJIO Festive Rush | E11: Beauty | F11: Van Heusen | G11: West | H11: Mobile Web | I11: COD | J11: Male | K11: 11 | L11: 343 | M11: 3773 | N11: 10 | O11: 377 | P11: 3396 | Q11: 1598 | R11: 1798 | S11: 1 | T11: 309 | U11: 4.1
A12: ORD00309 | B12: February | C12: 44974 | D12: AJIO Luxury Week | E12: Accessories | F12: Zara | G12: South | H12: App | I12: COD | J12: Female | K12: 8 | L12: 1577 | M12: 12616 | N12: 30 | O12: 3785 | P12: 8831 | Q12: 5497 | R12: 3334 | S12: 1 | T12: 1104 | U12: 4.5
A13: ORD00017 | B13: February | C13: 44975 | D13: AJIO Fashion Fiesta | E13: Clothing | F13: Van Heusen | G13: East | H13: Website | I13: COD | J13: Female | K13: 14 | L13: 3726 | M13: 52164 | N13: 5 | O13: 2608 | P13: 49556 | Q13: 23051 | R13: 26505 | S13: 2 | T13: 7079 | U13: 4.5
... A501: ORD00285 | B501: December | C501: 45287 | D501: AJIO Luxury Week | E501: Footwear | F501: Levis | G501: East | H501: Website | I501: Wallet | J501: Female | K501: 11 | L501: 4637 | M501: 51007 | N501: 0 | O501: 0 | P501: 51007 | Q501: 26038 | R501: 24969 | S501: 1 | T501: 4637 | U501: 4

Sheet PIVOT TABLE
B2: PIVOT CHART TABLE
B4: MONTHS | C4: Sum of Cost (₹) | E4: CATEGORY | F4: Sum of Cost (₹) | H4: REGIONS | I4: Sum of Cost (₹) | K4: BRAND | L4: Sum of Cost (₹) | N4: PAYMENT MODE | O4: Average of Cost (₹)
B5: January | C5: 235262 | E5: Accessories | F5: 676725 | H5: North | I5: 1020753 | K5: Adidas | L5: 581812 | N5: COD | O5: 8266.9231
B6: February | C6: 432204 | E6: Beauty | F6: 745159 | H6: South | I6: 1010751 | K6: H&M | L6: 387055 | N6: Credit Card | O6: 8456.7195
B7: March | C7: 279518 | E7: Clothing | F7: 541041 | H7: East | I7: 827285 | K7: HERE&NOW | L7: 514945 | N7: Debit Card | O7: 10341.119
B8: April | C8: 387890 | E8: Footwear | F8: 726779 | H8: West | I8: 1009056 | K8: Levis | L8: 582623 | N8: UPI | O8: 9962.9426
B9: May | C9: 515722 | E9: Home & Living | F9: 777116 | H9: Central | I9: 987012 | K9: Nike | L9: 497988 | N9: Wallet | O9: 11273.269
B10: June | C10: 238575 | E10: Kids | F10: 751427 | H10: (blank) | K10: Puma | L10: 498317 | N10: (blank)
B11: July | C11: 533333 | E11: Sports | F11: 636610 | H11: Grand Total | I11: 4854857 | K11: Roadster | L11: 489904 | N11: Grand Total | O11: 9709.714
B12: August | C12: 407751 | E12: (blank) | K12: Tokyo Talkies | L12: 376474
B13: September | C13: 441714 | E13: Grand Total | F13: 4854857 | K13: Van Heusen | L13: 477646
B14: October | C14: 421290 | K14: Zara | L14: 448093
B15: November | C15: 405336 | K15: (blank)
B16: December | C16: 556262 | K16: Grand Total | L16: 4854857
B17: (blank)
B18: Grand Total | C18: 4854857
B21: Count of Category | C21: CATEGORY
B22: GENDER | C22: Accessories | D22: Beauty | E22: Clothing | F22: Footwear | G22: Home & Living | H22: Kids | I22: Sports | J22: (blank) | K22: Grand Total
B23: Female | C23: 21 | D23: 28 | E23: 22 | F23: 18 | G23: 19 | H23: 27 | I23: 27 | K23: 162
B24: Male | C24: 22 | D24: 21 | E24: 22 | F24: 29 | G24: 33 | H24: 28 | I24: 25 | K24: 180
B25: Unisex | C25: 25 | D25: 30 | E25: 16 | F25: 17 | G25: 22 | H25: 28 | I25: 20 | K25: 158
B26: (blank)
B27: Grand Total | C27: 68 | D27: 79 | E27: 60 | F27: 64 | G27: 74 | H27: 83 | I27: 72 | K27: 500

Sheet DASHBOARD
A1: AJIO SALES INSIGHTS
C4: TOTAL REVENUE | G4: TOTAL ORDERS | J4: TOTAL UNITS SOLD | M4: NET REVENUE | Q4: GROSS PROFIT
C5: =SUM('Raw Data'!M:M) -> 10641857 | G5: =SUM('KPI Dashboard'!J7:K8) -> 500 | J5: =SUM('KPI Dashboard'!M7:N8) -> 3897 | M5: =SUM('Raw Data'!P:P) -> 8454342 | Q5: =SUM('Raw Data'!R:R) -> 3599485
